{"asset/lottie/coding.json":["asset/lottie/coding.json"],"asset/lottie/coding2.json":["asset/lottie/coding2.json"],"asset/lottie/coding3.json":["asset/lottie/coding3.json"],"asset/lottie/coding4.json":["asset/lottie/coding4.json"],"asset/me/me.jpeg":["asset/me/me.jpeg"],"asset/me/me.png":["asset/me/me.png"],"asset/me/me2.png":["asset/me/me2.png"],"asset/me/me3.png":["asset/me/me3.png"],"fonts/Anton-Regular.ttf":["fonts/Anton-Regular.ttf"],"fonts/PTSerif-Bold.ttf":["fonts/PTSerif-Bold.ttf"],"fonts/PTSerif-Regular.ttf":["fonts/PTSerif-Regular.ttf"],"fonts/RubikGlitch-Regular.ttf":["fonts/RubikGlitch-Regular.ttf"],"packages/cupertino_icons/assets/CupertinoIcons.ttf":["packages/cupertino_icons/assets/CupertinoIcons.ttf"]}