[{"family":"MaterialIcons","fonts":[{"asset":"fonts/MaterialIcons-Regular.otf"}]},{"family":"Anton-Regular","fonts":[{"asset":"fonts/Anton-Regular.ttf"}]},{"family":"PTSerif-Bold","fonts":[{"asset":"fonts/PTSerif-Bold.ttf"}]},{"family":"PTSerif-Regular","fonts":[{"asset":"fonts/PTSerif-Regular.ttf"}]},{"family":"RubikGlitch-Regular","fonts":[{"asset":"fonts/RubikGlitch-Regular.ttf"}]},{"family":"packages/cupertino_icons/CupertinoIcons","fonts":[{"asset":"packages/cupertino_icons/assets/CupertinoIcons.ttf"}]}]